{
    "nombre": "Juan",
    "edad": 30,
    "ciudad": "Buenos Aires",
    "intereses": [
      "música",
      "deportes",
      "viajes"
    ],
    "trabajo": {
      "empresa": "Acme Corp",
      "puesto": "Desarrollador"
    }
  }

/*{
    "quienesSomos": {
      "descripcion": "It is a long esta",
      "imagen": "pruebamarca.png"
    },
    "marcas": {
      "imagenes": [      {        "imagen": "pruebamarca.png"      },      {        "imagen": "pruebamarca1.png"      },      {        "imagen": "pruebamarca2.png"      }    ]
    }
  }*/
  